{
    "$schema": "../schemas/config-schema.json",
    "workspaces": [
        {
            "id": "rafaeltab",
            "root": "/home/rafaeltab/home/source/rafaeltab",
            "name": "Rafaeltab",
            "tags": []
        }
    ],
    "tmux": {
        "sessions": [
            {
                "name": "Rafaeltab main",
                "workspace": "rafaeltab",
                "windows": [
                    {
                        "name": "neovim",
                        "command": "nvim ."
                    },
                    {
                        "name": "rafaeltab"
                    }
                ]
            },
            {
                "workspace": "rafaeltab",
                "windows": [
                    {
                        "name": "rafaeltab"
                    }
                ]
            },
            {
                "name": "home",
                "path": "/home/rafaeltab",
                "windows": [
                    {
                        "name": "neovim",
                        "command": "nvim ."
                    }
                ]
            }
        ]
    }
}
